<?xml version="1.0" encoding="euc-kr"?>
<Window>
	<Form Height="576" Id="RBR1050" Left="8" OnLoadCompleted="fcFormLoadSetting" OnUnloadCompleted="fcFormUnloadProcess" PidAttrib="7" Title="경주개최&#32;준비상황보고(지점용)" Top="8" Ver="1.0" Width="816" WorkArea="true">
		<Datasets>
			<Dataset DataSetType="Dataset" Id="dsInComCd">
				<Contents>
					<colinfo id="DSNAME" size="20" summ="default" type="STRING"/>
					<colinfo id="CD_GRP_ID" size="6" summ="default" type="STRING"/>
					<colinfo id="QUERY_ID" size="256" summ="default" type="STRING"/>
					<colinfo id="TERM1" size="256" summ="default" type="STRING"/>
					<colinfo id="TERM2" size="256" summ="default" type="STRING"/>
					<colinfo id="TERM3" size="256" summ="default" type="STRING"/>
					<colinfo id="TERM4" size="256" summ="default" type="STRING"/>
					<colinfo id="TERM5" size="256" summ="default" type="STRING"/>
					<colinfo id="DESCRIPTION" size="256" summ="default" type="STRING"/>
					<colinfo id="ALL_YN" size="1" summ="default" type="STRING"/>
					<record>
						<ALL_YN></ALL_YN>
						<CD_GRP_ID></CD_GRP_ID>
						<DESCRIPTION></DESCRIPTION>
						<DSNAME>dsBrncCd</DSNAME>
						<QUERY_ID>rbr1050_s02</QUERY_ID>
						<TERM1></TERM1>
						<TERM2></TERM2>
						<TERM3></TERM3>
						<TERM4></TERM4>
						<TERM5></TERM5>
					</record>
					<record>
						<ALL_YN></ALL_YN>
						<CD_GRP_ID>169</CD_GRP_ID>
						<DESCRIPTION></DESCRIPTION>
						<DSNAME>dsAllClear</DSNAME>
						<QUERY_ID></QUERY_ID>
						<TERM1></TERM1>
						<TERM2></TERM2>
						<TERM3></TERM3>
						<TERM4></TERM4>
						<TERM5></TERM5>
					</record>
				</Contents>
			</Dataset>
			<Dataset DataSetType="Dataset" Id="dsMeetCd">
				<Contents>
					<colinfo id="CD" size="256" summ="default" type="STRING"/>
					<colinfo id="CD_NM" size="256" summ="default" type="STRING"/>
				</Contents>
			</Dataset>
			<Dataset DataSetType="Dataset" Id="dsRptPrepSitu"></Dataset>
			<Dataset DataSetType="Dataset" Id="dsRaceInfo"></Dataset>
			<Dataset DataSetType="Dataset" Id="ds_reportParam">
				<Contents>
					<colinfo id="PARAM_NM" size="256" type="STRING"/>
					<colinfo id="PARAM_VAL" size="256" type="STRING"/>
				</Contents>
			</Dataset>
			<Dataset DataSetType="Dataset" Id="dsBrncCd" OnLoadCompleted="fcdsOnLoadCompleted"></Dataset>
			<Dataset DataSetType="Dataset" Id="dsAllClear"></Dataset>
		</Datasets>
		<Shape BKColor="user0" Bottom="61" Height="29" Id="Shape1" Left="8" LineColor="user6" LineKind="Vertical" Right="809" RoundHeight="10" RoundUnit="Pixel" RoundWidth="10" TabOrder="7" Top="32" Type="RoundRect" Width="801"></Shape>
		<Image Height="20" Id="imgFormTitle" ImageID="m_titleblet" Left="8" TabOrder="0" Top="2" Width="17"></Image>
		<Static Color="user4" Height="22" Id="stFormTitle" Left="19" Style="snis_m_title" TabOrder="7" Text="경주개최&#32;준비상황보고" VAlign="Middle" Width="430"></Static>
		<Div Height="20" Id="divBtnLst" Left="437" TabOrder="7" Text="Div0" Url="common::comButtonType.xml" Width="374">
			<Contents></Contents>
		</Div>
		<Static Border="None" Height="20" Id="Static10" Left="20" Style="snis_if_lable" TabOrder="11" Text="경주일자" Top="36" VAlign="Middle" Width="50"></Static>
		<Calendar BindDataset="dsList" Border="Flat" Height="21" Id="calRaceDay" Left="81" OnChar="fcOnChar" SaturdayTextColor="blue" Style="snis_if_input01" SundayTextColor="red" TabOrder="13" Top="35" Width="90"></Calendar>
		<Radio BKColor="user0" BorderColor="user0" CodeColumn="CD" ColumnCount="4" DataColumn="CD_NM" Height="21" Hilight3dColor="user0" Id="rdoMeetCd" INDEX="0" InnerDataset="dsMeetCd" Left="188" OnChanged="fcOnChanged" ShadowColor="user0" TabOrder="14" Top="36" Width="120"></Radio>
		<Static Color="user4" Height="20" Id="stRaceInfo" Left="28" Style="snis_m_stitle" TabOrder="12" Text="경주개최&#32;준비현황" Top="72" VAlign="Middle" Width="254"></Static>
		<Image Height="20" Id="Image2" ImageID="m_titleblet2" Left="8" TabOrder="15" Top="74" Width="17"></Image>
		<Combo Border="Flat" CodeColumn="CD" DataColumn="CD_NM" Height="20" Id="cboBrncCd" ImeMode="none" InnerDataset="dsBrncCd" Left="344" OnChanged="fcCboOnChanged" ResetIndex="FIRST" Style="snis_if_input01" TabOrder="17" Top="36" Width="108">
			<Contents>
				<Record Data="&#32;" Default="true"/>
			</Contents>
		</Combo>
		<Static Align="Right" Border="None" Height="20" Id="Static0" Left="288" Style="snis_if_lable" TabOrder="16" Text="지점" Top="36" VAlign="Middle" Width="42"></Static>
		<Static Align="Center" BKColor="user0" Border="Flat" Height="183" Id="Static1" Left="13" Style="snis_m_lable" TabOrder="18" Text="주요점검사항" Top="204" VAlign="Middle" Width="94"></Static>
		<TextArea BindDataset="dsRptPrepSitu" Border="Flat" CheckLength="Byte" Column="CHK_POINT" Face3dColor="user4" Height="183" Id="taEvntCont" ImeMode="native" Left="108" MaxLength="2000" Style="snis_if_input01" TabOrder="5" Top="204" UserData="S" VScroll="TRUE" Width="701"></TextArea>
		<Static Align="Center" BKColor="user7" Border="Flat" Height="20" Id="Static2" Left="108" Style="snis_m_lable" TabOrder="19" Text="출근인원" Top="96" VAlign="Middle" Width="206"></Static>
		<MaskEdit Align="Center" BindDataset="dsRptPrepSitu" Border="Flat" Column="WRKG_NUM" DecimalLen="0" DigitLen="15" DisplayMaskchar="-" Height="20" Id="mskWrkgNum" Left="316" MaxLength="15" Style="snis_if_input01" TabOrder="1" Top="96" UserData="S" Width="52"></MaskEdit>
		<Static Align="Center" BKColor="user7" Border="Flat" Height="20" Id="Static3" Left="396" Style="snis_m_lable" TabOrder="20" Text="휴가인원" Top="96" VAlign="Middle" Width="206"></Static>
		<MaskEdit Align="Center" BindDataset="dsRptPrepSitu" Border="Flat" Column="DUTY_OFF_NUM" DecimalLen="0" DigitLen="15" DisplayMaskchar="-" Height="20" Id="MaskEdit0" Left="604" MaxLength="15" Style="snis_if_input01" TabOrder="2" Top="96" UserData="S" Width="52"></MaskEdit>
		<Static Align="Center" BKColor="user0" Border="Flat" Height="159" Id="Static4" Left="13" Style="snis_m_lable" TabOrder="21" Text="특이사항" Top="388" VAlign="Middle" Width="94"></Static>
		<TextArea BindDataset="dsRptPrepSitu" Border="Flat" CheckLength="Byte" Column="SIGNFT_POINT" Face3dColor="user4" Height="159" Id="TextArea0" ImeMode="native" Left="108" MaxLength="2000" Style="snis_if_input01" TabOrder="6" Top="388" UserData="S" VScroll="TRUE" Width="701"></TextArea>
		<Static Align="Center" BKColor="user7" Border="Flat" Height="20" Id="Static5" Left="684" Style="snis_m_lable" TabOrder="22" Text="이상유무" Top="96" VAlign="Middle" Width="124"></Static>
		<Static Height="20" Id="Static6" Left="108" TabOrder="23" Text="※&#32;인원과&#32;특이사항은&#32;영업총괄팀에&#32;보고되어지는&#32;내용입니다." Top="552" VAlign="Middle" Width="508"></Static>
		<Static Height="14" Id="Static7" Left="376" TabOrder="24" Text="명" Top="101" Width="16"></Static>
		<Static Height="14" Id="Static8" Left="660" TabOrder="25" Text="명" Top="101" Width="16"></Static>
		<Grid BindDataset="dsRptPrepSitu" BkColor2="default" BoldHead="true" Bottom="371" Enable="true" EndLineColor="default" Height="39" Id="grdRptPrepSitu" InputPanel="FALSE" Left="748" LineColor="default" Right="798" TabOrder="26" TabStop="true" Top="332" UseDBuff="true" UsePopupMenu="true" UseSelColor="true" Visible="FALSE" VLineColor="default" WheelScrollRow="1" Width="50"></Grid>
		<Static Color="HIGHLIGHT" Height="20" Id="stRaceDesc" Left="160" Style="snis_m_stitle" TabOrder="27" Top="72" VAlign="Middle" Width="340"></Static>
		<Static Align="Center" BKColor="user0" Border="Flat" Height="107" Id="Static9" Left="12" Style="snis_m_lable" TabOrder="28" Text="출근사항" Top="96" VAlign="Middle" Width="94"></Static>
		<TextArea BindDataset="dsRptPrepSitu" Border="Flat" CheckLength="Byte" Column="WRKG_INFO" Face3dColor="user4" Height="84" Id="TextArea1" ImeMode="native" Left="108" MaxLength="2000" Style="snis_if_input01" TabOrder="3" Top="118" UserData="S" VScroll="TRUE" Width="284"></TextArea>
		<TextArea BindDataset="dsRptPrepSitu" Border="Flat" CheckLength="Byte" Column="DUTY_OFF_INFO" Face3dColor="user4" Height="84" Id="TextArea2" ImeMode="native" Left="396" MaxLength="2000" Style="snis_if_input01" TabOrder="4" Top="118" UserData="S" VScroll="TRUE" Width="284"></TextArea>
		<Button ButtonStyle="TRUE" Cursor="HAND" Height="20" Id="btnEndSave" ImageID="btn_txt_08" Left="708" OnClick="fcCopy" TabOrder="29" Text="전일자료&#32;복사" Top="36" Width="86"></Button>
		<Radio BindDataset="dsRptPrepSitu" Border="None" BorderColor="user3" CodeColumn="CD" Column="CHK_POINT_RSLT" DataColumn="CD_NM" Font="Default,9" Height="46" Id="Radio0" INDEX="-1" InnerDataset="dsAllClear" Left="696" TabOrder="30" Top="118" Width="112"></Radio>
	</Form>
	<Script><![CDATA[
/***************************************************************************************************
*                                         공통 Script Include                                      *
***************************************************************************************************/
#include "lib::rbm_common_script.js";
#include "lib::rbm_app_script.js";

/***************************************************************************************************
*                                          화면 변수 선언부                                        *
***************************************************************************************************/
var sFormId       = this.GetForm().id;
var sBUTTONLIST   = 'TTTTTT';                          //공통기능정의(버튼순으로 T or F)
var sUSERAUTH     = '';                                //사용자별 프로그램 사용 권한
var sFORMCAPTION  = '';                                //Form의 Title 정보
var sFORMLOCATION = '';                                //Form의 Location 정보
var sUSERLAVEL    = '';                                //Form의 사용  Level
var vREVOBJ       = Array(9);                          //결과값 처리를 위한 오브젝트 
var sGRDTIT       = "";                                //그리드 제목
var sCUROBJ       ;                                    //현재 LOST FOCUS 오브젝트

var sMenuGrpNum     = "0";                         // 메뉴그룹의 갯수보관
var sMenuListNum    = "0";                          // 메뉴리스트의 갯수보관
var sMenuUpId       = "";
var sMenuUpNm       = "";
/***************************************************************************************************
*                                         공통 Event 처리 부분                                     *
***************************************************************************************************/
/*-------------------------------------------------------------------------------------------------+
>>  최초 화면 Load時 처리 할 사항
+-------------------------------------------------------------------------------------------------*/
function fcFormLoadSetting(obj) {  

    sBUTTONLIST   = 'FTTFTTT';   // T초기화,T조회,F저장,F삭제,T엑셀,F인쇄,T닫기
  
 	//화면환경 설정
	sFORMCAPTION  = obj.Title;
	sFORMLOCATION = "";

	//화면 정보 Display 및 Button 권한 설정
	fnc_FormLoadSetting(obj, sFORMCAPTION, sFORMLOCATION, sBUTTONLIST, sUSERAUTH);
	
	fcd_GetComboDs(dsInComCd);

	// if (IsExistVar("sApro", true)) {
		// if (sApro != "T") dsBrncCd.Filter("CD='"+gdsUser.GetColumn(0, "BRNC_CD")+"'");
		// else              dsBrncCd.UnFilter(); 
		// cboBrncCd.Value = gdsUser.GetColumn(0, "BRNC_CD");
	// }
	calRaceDay.Value = fcd_GetSysdate("YYYYMMDD");				// 시스템의 오늘날짜	
	
	fcSearch(); // 경주구분 코드부터 검색
    
}
/*-------------------------------------------------------------------------------------------------+
>>  최초 화면 UNLoad時 처리 할 사항
+-------------------------------------------------------------------------------------------------*/
function fcFormUnloadProcess(obj) {
	// 자료 변경 여부를 체크하고자 하는 DataSet Object를 넘긴다.
	var sDataset = "dsRptPrepSitu";
	if (   !fnc_FormUnloadCheck(sDataset, sFormId) ) return false;
}

/*-------------------------------------------------------------------------------------------------+
>>  단축키 처리(Form KeyDown)
+-------------------------------------------------------------------------------------------------*/
function fcHotKey(obj,objSenderObj,nChar,bShift,bControl,bAlt,nLLParam,nHLParam) {

	// Return Key Press時 Next Component focus
	if ( nChar == 13 ) {
		var oFocusComponent = GetNextComponent(true);
		oFocusComponent.setfocus();
		return;
	}
}

/***************************************************************************************************
*                                      공통 버튼 Event 처리 부분                                   *
***************************************************************************************************/
/*-------------------------------------------------------------------------------------------------+
>>  취소 버튼 클릭 時 처리
+-------------------------------------------------------------------------------------------------*/
function fcInit(obj) {
	dsRptPrepSitu.ClearData();	
}


/*-------------------------------------------------------------------------------------------------+
>>  조회 버튼 클릭 時 필수조건 체크 및 그리드 초기화
+-------------------------------------------------------------------------------------------------*/
function fcSearchCheck(obj) {
	fcInit(obj);

	return true;
}

/*-------------------------------------------------------------------------------------------------+
>>  조회 버튼 클릭 時 처리
+-------------------------------------------------------------------------------------------------*/
function fcSearch(obj) {
	var sServiceName = "rsm2010-service:searchMeetCd";  // Grid 조회
	var sInDataSet   = "";
	var sOutDataSet  = "dsMeetCd=dsMeetCd";     
	
	fcd_AddParam("RACE_DAY", calRaceDay.Value);    
	fcd_SendTransaction(sServiceName, sInDataSet, sOutDataSet, "fcCallBack", false);
}

function fcSearchInfo(obj) {
	if ( !fcSearchCheck(obj) ) return;

	var sServiceName = "rbr1050-service:searchRaceInfo";
	var sInDataSet   = "";
	var sOutDataSet  = "dsRaceInfo=dsRaceInfo dsRptPrepSitu=dsRptPrepSitu";

	fcd_AddParam("RACE_DAY", calRaceDay.Value);    
	fcd_AddParam("BRNC_CD",  cboBrncCd.Value);

	fcd_SendTransaction(sServiceName, sInDataSet, sOutDataSet, "fcCallBack", true);
}

/*-------------------------------------------------------------------------------------------------+
>>  저장 하기전에 필수항목 체크
+-------------------------------------------------------------------------------------------------*/
function fcSaveCheck(obj) {
	// 변경된 자료가 있는지 체크
	if ( !fnc_DatasetChangeCheck(dsRptPrepSitu) ) {
		// 저장 할 자료가 없음
		fnc_Message(SNIS_COM_1006, "N");
		return false;
	}

	// 필수항목체크
	oDataSet          = dsRptPrepSitu;
	sMandatoryColID   = "RACE_DAY|COMM_NO";
	sMandatoryColName = "경주일자|지점";
	oGrid             = grdRptPrepSitu;
	
	if ( fnc_GetMandatoryViolateRow(oDataSet, sMandatoryColID, sMandatoryColName, oGrid) > -1 ) {
		return false;
	}
	
	return true;
}

/*-------------------------------------------------------------------------------------------------+
>>  저장 버튼 클릭 時 처리
+-------------------------------------------------------------------------------------------------*/
function fcSave(obj) {
	if ( !fcSaveCheck() ) return;

	var sServiceName = "";
	var sInDataSet   = "";
	var sOutDataSet  = "";

	sServiceName = "rbr1050-service:saveRptPrepSitu";
	sInDataSet   = "dsRptPrepSitu=dsRptPrepSitu:u ";
	sOutDataSet  = "dsRptPrepSitu=dsRptPrepSitu ";

	fcd_AddParam("RACE_DAY", calRaceDay.Value);    
	fcd_AddParam("BRNC_CD",  cboBrncCd.Value);

	fcd_SendTransaction(sServiceName, sInDataSet, sOutDataSet, "fcCallBack", false);
}

/*-------------------------------------------------------------------------------------------------+
>>  행추가 버튼 클릭 時 처리
+-------------------------------------------------------------------------------------------------*/
function fcAddRow(obj) {
	// DataSet의 Header 정보가 있을 때  Add 처리
	switch ( obj.GetForm().id ) {

	}
}


/*-------------------------------------------------------------------------------------------------+
>>  행삽입 버튼 클릭 時 처리
+-------------------------------------------------------------------------------------------------*/
function fcInsRow(obj) {
	
}


/*-------------------------------------------------------------------------------------------------+
>>  행삭제 버튼 클릭 時 처리
+-------------------------------------------------------------------------------------------------*/
function fcDelRow(obj) {
	// DataSet의 Header 정보가 있을 때  Add 처리
	switch ( obj.GetForm().id ) {
		case "dsRptPrepSitu" :
			if ( !fnc_DeleteCheck(dsRptPrepSitu, "chk", "1") ) return;

			break;

	}
}


/*-------------------------------------------------------------------------------------------------+
>>  엑셀 버튼 클릭 時 처리
+-------------------------------------------------------------------------------------------------*/
function fcToExcel(obj) {
	var sExcelList = "grdRptPrepSitu:경주개최 준비상황보고";
	fcd_OpenExcelListExport(sExcelList,1);
}

/*-------------------------------------------------------------------------------------------------+
>>  인쇄
+-------------------------------------------------------------------------------------------------*/
function fcPrint(){
			
	//데이터셋을 초기화 한다.
	ds_reportParam.DeleteAll();
	var nRnum;
		
	// 필드 값을 셋팅한다.
	var paramField = [
							"RACE_DAY"						// 경주일자  
						   ,"BRNC_CD"
					 ];

	// 값을 셋팅한다.
	var paramValue = [
							calRaceDay.Value
						   ,cboBrncCd.Value
					 ];
					 
	
	var rowCnt = paramField.length;	
	for(var row = 0 ; row < rowCnt; row++)
	{
		nRnum = ds_reportParam.AppendRow();
		ds_reportParam.SetColumn(nRnum, "PARAM_NM", paramField[row]);
		ds_reportParam.SetColumn(nRnum, "PARAM_VAL",paramValue[row]);
	}
			
	/* 레포트 배율 추가 - 시작 */
	iRow = ds_reportParam.AddRow();

	// Default Scale 파라미터명 추가(고정)
	ds_reportParam.SetColumn(iRow, "PARAM_NM", "DEFAULT_SCALE");
	ds_reportParam.SetColumn(iRow, "PARAM_VAL", "1");
	
	//레포트 트랙잭션을 태운다.
	fnc_ReportPreView("rbr1050", ds_reportParam.ID, "Y");		
}

/*-------------------------------------------------------------------------------------------------+
>>  화면 종료(닫기) 버튼 클릭 時 처리
+-------------------------------------------------------------------------------------------------*/
function fcEnd(obj) {
	// 화면 종료
	Close();
}

/***************************************************************************************************
*                                      공통 Function 처리 부분                                     *
***************************************************************************************************/
/*-------------------------------------------------------------------------------------------------+
>>  Text Box가 Focus를 받을 때
+-------------------------------------------------------------------------------------------------*/
function fcEditFocus(obj) {
	// fnc_EditFocus(obj);
}

/*-------------------------------------------------------------------------------------------------+
>>  그리드 정렬
+-------------------------------------------------------------------------------------------------*/
function fcGridSort(obj,nCell,nX,nY) {
	// 특정 Head 클릭 시 해당 항목으로 Sort(만약 특정 컬럼을 누를때만 소트하고자 한다면 nCell로 조건)
	if ( nCell == 0 ) {
 		fnc_GridAllChk(obj);
	} else {
		fnc_GridSort(obj, object(obj.BindDataset), nCell);
	}
}

/*-------------------------------------------------------------------------------------------------+
>>  Help Popup Open
+-------------------------------------------------------------------------------------------------*/
function fcHelpDialoge(obj,nX,nY) {

}

/*-------------------------------------------------------------------------------------------------+
>>  그리드에서 팝업 처리
+-------------------------------------------------------------------------------------------------*/
function fcGrdOnExpandEdit(objGrd, nRow, nCell, strVal, nPivotIndex) {

}

/***************************************************************************************************
*                                      사용자 정의  처리 부분                                      *
***************************************************************************************************/
/*-------------------------------------------------------------------------------------------------+
>>  Transaction 후 처리 해야 할 내용!
+-------------------------------------------------------------------------------------------------*/
function fcCallBack(sServiceName, ErrorCode, ErrorMSG) {
	if ( !fnc_result(ErrorCode, ErrorMSG) ) return;

    if(sServiceName == "rsm2010-service:searchMeetCd") {
		rdoMeetCd.Value = dsMeetCd.GetColumn(0,"CD");			
		if(dsMeetCd.rowcount > 0) { // 경주일이 있을 경우만 검색
			fcSearchInfo();
		} else {
			fcInit();
		}
		return;
		
    } else if (sServiceName == "rbr1050-service:searchRaceInfo") {
		if (dsRptPrepSitu.rowcount() == 0) {
			var nRow = dsRptPrepSitu.AddRow();
			dsRptPrepSitu.SetColumn(nRow, "RACE_DAY", calRaceDay.Value);
			dsRptPrepSitu.SetColumn(nRow, "COMM_NO",  cboBrncCd.Value);
		}
		stRaceDesc.text = dsRaceInfo.GetColumn(0, "RACE_INFO");
		mskWrkgNum.SetFocus();
		
    } else if (sServiceName == "rbr1050-service:copyRptPrepSitu") {
		if (dsRptPrepSitu.rowcount() == 0) {
			fnc_message("복사할 자료가 없습니다.");
			
			var nRow = dsRptPrepSitu.AddRow();
			dsRptPrepSitu.SetColumn(nRow, "RACE_DAY", calRaceDay.Value);
			dsRptPrepSitu.SetColumn(nRow, "COMM_NO",  cboBrncCd.Value);
		}
		stRaceDesc.text = dsRaceInfo.GetColumn(0, "RACE_INFO");
		mskWrkgNum.SetFocus();
    }

}




/*-------------------------------------------------------------------------------------------------+
>> Enter Key 이벤트시 조회되도록 한다.
+-------------------------------------------------------------------------------------------------*/


function fcOnChanged(obj,strCode,strText,nOldIndex,nNewIndex)
{
	if(obj.Id == "cboBrncCd"){
		fcSearch();
	}

}


function fcCboOnChanged(obj,strCode,strText,nOldIndex,nNewIndex)
{
	if (obj.id == "cboBrncCd") fcSearch(obj);
}



function fcdsOnLoadCompleted(obj,nErrorCode,strErrorMsg,nReason)
{
	if (obj.id == "dsBrncCd" && nReason == 0) {
		if (sApro != "T") dsBrncCd.Filter("CD='"+fcGetBrncCd()+"'");
		else              dsBrncCd.UnFilter(); 
		cboBrncCd.Value = fcGetBrncCd();
	}
}

function fcCopy(obj)
{
	if (!fnc_IsNull(dsRptPrepSitu.GetColumn(0, "STAT"))) {
		if (fnc_message("전일자료로 복사시 기존자료가 삭제됩니다.","Y") != true) return;
	}

	var sServiceName = "";
	var sInDataSet   = "";
	var sOutDataSet  = "";

	sServiceName = "rbr1050-service:copyRptPrepSitu";
	sInDataSet   = "dsRptPrepSitu=dsRptPrepSitu:u ";
	sOutDataSet  = "dsRptPrepSitu=dsRptPrepSitu ";

	fcd_AddParam("RACE_DAY", calRaceDay.Value);    
	fcd_AddParam("BRNC_CD",  cboBrncCd.Value);
	fcd_AddParam("MEET_CD",  rdoMeetCd.Value);

	fcd_SendTransaction(sServiceName, sInDataSet, sOutDataSet, "fcCallBack", false);
}

function fcGetBrncCd()
{
	var sBrncCd = "";
	var nRow = dsBrncCd.FindRow("CD_NM2", gdsUser.GetColumn(0, "TEAM_CD"));
	if (nRow > -1) sBrncCd = dsBrncCd.GetColumn(nRow, "CD");
	else sBrncCd = gdsUser.GetColumn(0, "BRNC_CD");
	return sBrncCd;
}]]></Script>
</Window>